gr_lora_sdr_profiler/__init__.py
gr_lora_sdr_profiler/__main__.py
gr_lora_sdr_profiler/cran.py
gr_lora_sdr_profiler/file_saver.py
gr_lora_sdr_profiler/file_writer.py
gr_lora_sdr_profiler/frame_detector_threshold.py
gr_lora_sdr_profiler/frame_detector_timeout.py
gr_lora_sdr_profiler/get_config.py
gr_lora_sdr_profiler/get_cpu_load.py
gr_lora_sdr_profiler/plotter.py
gr_lora_sdr_profiler/run_flowgraph.py
gr_lora_sdr_profiler/time_estimater.py
gr_lora_sdr_profiler/bash_scripts/convert.sh
gr_lora_sdr_profiler/bash_scripts/run.sh
gr_lora_sdr_profiler/templates/base.py
gr_lora_sdr_profiler/templates/cran_send.py
gr_lora_sdr_profiler/templates/frame_detector_threshold.py
gr_lora_sdr_profiler/templates/frame_detector_timeout.py
gr_lora_sdr_profiler/templates/lora_sim_blocks
gr_lora_sdr_profiler/templates/lora_sim_chain
gr_lora_sdr_profiler/templates/lora_sim_multi1
gr_lora_sdr_profiler/templates/lora_sim_multi2
gr_lora_sdr_profiler/templates/lora_sim_multi3
gr_lora_sdr_profiler/templates/lora_sim_multi4
gr_lora_sdr_profiler/templates/lora_sim_multi5
gr_lora_sdr_profiler/templates/lora_sim_multi6
gr_lora_sdr_profiler-0.29.dist-info/entry_points.txt
gr_lora_sdr_profiler-0.29.dist-info/LICENSE
gr_lora_sdr_profiler-0.29.dist-info/WHEEL
gr_lora_sdr_profiler-0.29.dist-info/METADATA
gr_lora_sdr_profiler-0.29.dist-info/RECORD
