Metadata-Version: 2.1
Name: gr_lora_sdr_profiler
Version: 0.29
Summary: gr_lora_sdr_profiler
Home-page: https://github.com/martynvdijke/gr-lora_sdr-profiler
Author: Martyn van Dijke
Author-email: martijnvdijke600@gmail.com
Requires-Python: >=3.7
Classifier: License :: OSI Approved :: MIT License
Requires-Dist: flit_core>=2.2.0
Requires-Dist: coloredlogs
Requires-Dist: prompt_toolkit
Requires-Dist: pandas
Requires-Dist: wandb
